jsw_pillow/__init__.py
jsw_pillow/modules/__init__.py
jsw_pillow/modules/converter.py
jsw_pillow/modules/get_position.py
jsw_pillow/modules/std_source.py
jsw_pillow/modules/thumbnail.py
jsw_pillow/modules/watermark.py
jsw_pillow-1.0.24.dist-info/METADATA
jsw_pillow-1.0.24.dist-info/WHEEL
jsw_pillow-1.0.24.dist-info/top_level.txt
jsw_pillow-1.0.24.dist-info/RECORD
