Metadata-Version: 2.4
Name: jsw-pillow
Version: 1.0.24
Requires-Dist: pillow>=11.3.0
Requires-Dist: python-resize-image>=1.1.20
Requires-Dist: requests>=2.32.4
